odoo/addons/web_widget_product_label_section_and_note_full_label_sale/README.rst
odoo/addons/web_widget_product_label_section_and_note_full_label_sale/__init__.py
odoo/addons/web_widget_product_label_section_and_note_full_label_sale/__manifest__.py
odoo/addons/web_widget_product_label_section_and_note_full_label_sale/i18n/web_widget_product_label_section_and_note_full_label_sale.pot
odoo/addons/web_widget_product_label_section_and_note_full_label_sale/readme/CONTRIBUTORS.md
odoo/addons/web_widget_product_label_section_and_note_full_label_sale/readme/DESCRIPTION.md
odoo/addons/web_widget_product_label_section_and_note_full_label_sale/static/description/icon.png
odoo/addons/web_widget_product_label_section_and_note_full_label_sale/static/description/index.html
odoo/addons/web_widget_product_label_section_and_note_full_label_sale/static/src/sale_product_field/sale_product_field.esm.js
odoo/addons/web_widget_product_label_section_and_note_full_label_sale/static/src/sale_product_field/sale_product_field.xml
odoo_addon_web_widget_product_label_section_and_note_full_label_sale-18.0.1.0.0.2.dist-info/METADATA
odoo_addon_web_widget_product_label_section_and_note_full_label_sale-18.0.1.0.0.2.dist-info/WHEEL
odoo_addon_web_widget_product_label_section_and_note_full_label_sale-18.0.1.0.0.2.dist-info/top_level.txt
odoo_addon_web_widget_product_label_section_and_note_full_label_sale-18.0.1.0.0.2.dist-info/RECORD
