Metadata-Version: 2.1
Name: odoo-addon-web_widget_product_label_section_and_note_full_label_sale
Version: 18.0.1.0.0.2
Requires-Python: >=3.10
Requires-Dist: odoo-addon-web_widget_product_label_section_and_note_full_label==18.0.*
Requires-Dist: odoo==18.0.*
Summary: Glue module between web_widget_product_label_section_and_note_full_label and sale.
Home-page: https://github.com/OCA/sale-workflow
License: AGPL-3
Author: ForgeFlow, Odoo Community Association (OCA)
Author-email: support@odoo-community.org
Classifier: Programming Language :: Python
Classifier: Framework :: Odoo
Classifier: Framework :: Odoo :: 18.0
Classifier: License :: OSI Approved :: GNU Affero General Public License v3
